{
  "ComplEx": {
    "hits_at_3": [
      4.01,
      8.06,
      10.53,
      13.6,
      16.79,
      19.67,
      23.86,
      27.94,
      21.29,
      4.35
    ],
    "hits_at_10": [
      6.65,
      12.11,
      17.04,
      21.34,
      26.13,
      30.17,
      35.59,
      39.91,
      36.78,
      13.74
    ],
    "mr": [
      31709.3368,
      23177.9784,
      14049.1208,
      10065.7686,
      7449.494,
      6405.6785,
      4394.9085,
      3480.4018,
      2728.1506,
      1990.0285
    ],
    "mrr": [
      0.04,
      0.07,
      0.091,
      0.11,
      0.135,
      0.163,
      0.196,
      0.235,
      0.18,
      0.052
    ],
    "hits_at_1": [
      2.41,
      4.2,
      5.1,
      6.4,
      8.02,
      9.39,
      11.55,
      14.79,
      8.73,
      1.36
    ],
    "hits_at_5": [
      5.03,
      9.71,
      13.07,
      16.96,
      20.57,
      24.56,
      29.37,
      33.06,
      27.99,
      7.22
    ]
  },
  "TransE": {
    "hits_at_3": [
      2.41,
      3.65,
      4.3,
      3.29,
      3.54,
      3.98,
      6.09,
      5.04,
      3.86,
      3.96
    ],
    "hits_at_10": [
      5.31,
      6.69,
      7.89,
      7.51,
      7.8,
      7.78,
      10.79,
      9.88,
      8.78,
      8.9
    ],
    "mr": [
      22293.3014,
      11679.3533,
      7509.0975,
      6015.8409,
      5195.8952,
      4294.9721,
      3818.2328,
      3621.4695,
      3703.6431,
      3454.8445
    ],
    "mrr": [
      0.026,
      0.04,
      0.047,
      0.039,
      0.04,
      0.041,
      0.066,
      0.053,
      0.044,
      0.043
    ],
    "hits_at_1": [
      1.7,
      2.31,
      2.75,
      2.42,
      2.47,
      2.75,
      4.34,
      2.95,
      2.49,
      2.65
    ],
    "hits_at_5": [
      3.39,
      4.76,
      5.42,
      4.54,
      4.7,
      4.85,
      7.78,
      6.63,
      5.68,
      5.43
    ]
  },
  "DistMult": {
    "hits_at_3": [
      4.55,
      7.48,
      10.74,
      13.53,
      16.76,
      20.17,
      23.62,
      28.39,
      21.9,
      23.46
    ],
    "hits_at_10": [
      7.23,
      12.7,
      17.33,
      21.29,
      25.25,
      30.47,
      35.2,
      39.81,
      36.7,
      41.65
    ],
    "mr": [
      32244.8654,
      21182.1146,
      14786.9934,
      10248.6625,
      8469.8005,
      6460.9006,
      4291.5298,
      3217.7621,
      2784.2237,
      1962.3036
    ],
    "mrr": [
      0.044,
      0.067,
      0.094,
      0.113,
      0.138,
      0.168,
      0.195,
      0.24,
      0.185,
      0.202
    ],
    "hits_at_1": [
      2.79,
      4.15,
      5.18,
      6.42,
      7.41,
      9.05,
      11.21,
      15.14,
      9.55,
      10.9
    ],
    "hits_at_5": [
      5.58,
      9.18,
      12.84,
      17.19,
      20.55,
      24.58,
      29.12,
      33.4,
      28.09,
      31.84
    ]
  }
}