{
  "DistMult": {
    "hits_at_3": [
      7.53,
      13.13,
      17.21,
      20.73,
      24.34,
      28.62,
      31.61,
      35.26,
      40.13,
      45.4
    ],
    "mrr": [
      0.063,
      0.111,
      0.145,
      0.176,
      0.202,
      0.236,
      0.259,
      0.29,
      0.33,
      0.389
    ],
    "hits_at_1": [
      4.6,
      7.45,
      9.19,
      10.83,
      12.51,
      14.7,
      16.43,
      18.68,
      22.81,
      29.47
    ],
    "mr": [
      10107.4607,
      7543.5167,
      5240.4442,
      3833.0534,
      2910.1249,
      2294.142,
      2034.323,
      1591.708,
      1311.4821,
      1198.8688
    ],
    "hits_at_5": [
      8.58,
      15.61,
      20.76,
      25.29,
      29.92,
      34.5,
      37.1,
      42.14,
      46.34,
      50.64
    ],
    "hits_at_10": [
      9.98,
      18.42,
      25.01,
      30.88,
      35.84,
      41.37,
      44.6,
      48.65,
      51.9,
      56.24
    ]
  },
  "TransE": {
    "hits_at_3": [
      6.59,
      9.8,
      12.27,
      13.46,
      13.26,
      13.99,
      13.5,
      14.45,
      13.81,
      14.86
    ],
    "mrr": [
      0.06,
      0.091,
      0.103,
      0.11,
      0.1,
      0.119,
      0.111,
      0.108,
      0.12,
      0.121
    ],
    "hits_at_1": [
      3.69,
      4.52,
      5.0,
      5.91,
      5.66,
      5.99,
      5.84,
      5.34,
      6.09,
      6.39
    ],
    "mr": [
      7908.4488,
      4155.7421,
      2581.5013,
      1841.2188,
      1505.3713,
      1289.8824,
      1199.6016,
      1135.159,
      1067.8952,
      1002.9066
    ],
    "hits_at_5": [
      9.37,
      14.11,
      16.47,
      18.26,
      18.85,
      18.65,
      18.5,
      19.47,
      19.04,
      19.06
    ],
    "hits_at_10": [
      11.68,
      19.9,
      22.8,
      25.05,
      24.42,
      25.75,
      25.56,
      26.29,
      25.81,
      25.22
    ]
  },
  "ComplEx": {
    "hits_at_3": [
      6.73,
      13.28,
      18.41,
      23.06,
      26.82,
      30.48,
      34.77,
      40.16,
      44.79,
      51.41
    ],
    "mrr": [
      0.06,
      0.116,
      0.159,
      0.191,
      0.226,
      0.258,
      0.288,
      0.322,
      0.362,
      0.418
    ],
    "hits_at_1": [
      4.56,
      8.34,
      11.01,
      12.71,
      15.1,
      17.44,
      19.5,
      22.12,
      25.78,
      31.06
    ],
    "mr": [
      10146.0919,
      7319.0869,
      5192.3306,
      3829.9378,
      2895.9634,
      2273.6704,
      1901.5517,
      1597.6567,
      1328.7197,
      1093.24
    ],
    "hits_at_5": [
      7.47,
      15.35,
      21.48,
      26.98,
      31.56,
      36.17,
      40.23,
      45.56,
      49.34,
      54.62
    ],
    "hits_at_10": [
      8.76,
      17.77,
      25.55,
      31.27,
      36.83,
      41.95,
      45.57,
      49.6,
      53.36,
      57.25
    ]
  }
}